tf_logger/__init__.py
tf_logger/test_tf_logger.py
tf_logger/tf_logger.py
tf_logger-1.1.1.dist-info/METADATA
tf_logger-1.1.1.dist-info/RECORD
tf_logger-1.1.1.dist-info/WHEEL
tf_logger-1.1.1.dist-info/top_level.txt
