Metadata-Version: 2.1
Name: tf-logger
Version: 1.1.1
Summary: A print and debugging utility that makes your error printouts look nice
Home-page: https://github.com/episodeyang/tf_logger
Author: Ge Yang
Author-email: yangge1987@gmail.com
License: UNKNOWN
Keywords: tf_logger,tensorflow,logging,debug,debugging
Platform: UNKNOWN
Classifier: Development Status :: 4 - Beta
Classifier: Intended Audience :: Science/Research
Classifier: Programming Language :: Python :: 3
Requires-Dist: typing
Requires-Dist: tensorflow
Requires-Dist: numpy
Requires-Dist: termcolor
Requires-Dist: pprint
